microplate/__init__.py
microplate/mtp.py
microplate-1.8.dist-info/licenses/LICENSE
microplate-1.8.dist-info/METADATA
microplate-1.8.dist-info/WHEEL
microplate-1.8.dist-info/top_level.txt
microplate-1.8.dist-info/RECORD
