Metadata-Version: 2.4
Name: microplate
Version: 1.8
Summary: A package for dealing with microtiter plates
Author-email: Justin Shumate <shumatejr@gmail.com>
License-Expression: MIT
Project-URL: Homepage, https://github.com/shumatejr/microplate
Project-URL: Changelog, https://github.com/shumatejr/microplate/blob/main/CHANGELOG.md
Project-URL: Issues, https://github.com/shumatejr/microplate/issues
Keywords: titer,microtiter,plate,assay,reader,lab
Classifier: Programming Language :: Python :: 3
Classifier: Operating System :: OS Independent
License-File: LICENSE
Requires-Dist: numpy
Dynamic: license-file
